agentschema/__init__.py
agentschema/core/_AgentDefinition.py
agentschema/core/_AgentManifest.py
agentschema/core/_Binding.py
agentschema/core/_Connection.py
agentschema/core/_EnvironmentVariable.py
agentschema/core/_Format.py
agentschema/core/_McpServerApprovalMode.py
agentschema/core/_Model.py
agentschema/core/_ModelOptions.py
agentschema/core/_Parser.py
agentschema/core/_Property.py
agentschema/core/_PropertySchema.py
agentschema/core/_ProtocolVersionRecord.py
agentschema/core/_Resource.py
agentschema/core/_Template.py
agentschema/core/_Tool.py
agentschema/core/__init__.py
agentschema/core/_context.py
agentschema/core/py.typed
agentschema/py.typed
agentschema-1.0.0b2.dist-info/WHEEL
agentschema-1.0.0b2.dist-info/METADATA
agentschema-1.0.0b2.dist-info/RECORD
