Metadata-Version: 2.3
Name: agentschema
Version: 1.0.0b2
Summary: Declarative Agent Schema
Requires-Dist: pyyaml>=6.0.1
Requires-Dist: python-dotenv>=1.0.1
Requires-Dist: click>=8.1.7
Requires-Dist: aiofiles>=24.1.0
Requires-Dist: ruff>=0.13.3
Requires-Dist: black>=25.9.0
Requires-Dist: pytest ; extra == 'dev'
Requires-Dist: pytest-asyncio ; extra == 'dev'
Requires-Dist: ruff ; extra == 'dev'
Requires-Dist: mypy ; extra == 'dev'
Requires-Dist: types-aiofiles ; extra == 'dev'
Requires-Dist: types-pyyaml ; extra == 'dev'
Requires-Dist: pytest-cov ; extra == 'dev'
Requires-Dist: black ; extra == 'dev'
Requires-Python: >=3.11
Provides-Extra: dev
